wallabag/__init__.py
wallabag/datetime_helpers.py
wallabag/errors.py
wallabag/wallabag.py
py_wallabag-0.0.8.dist-info/METADATA
py_wallabag-0.0.8.dist-info/WHEEL
py_wallabag-0.0.8.dist-info/top_level.txt
py_wallabag-0.0.8.dist-info/RECORD
