Metadata-Version: 2.1
Name: py-wallabag
Version: 0.0.8
Summary: Python wrapper for the Wallabag Rest API
Home-page: https://github.com/zeroone2numeral2/py-wallabag
Author: zeroone2numeral2
License: MIT
Platform: UNKNOWN
Classifier: Development Status :: 3 - Alpha
Classifier: Programming Language :: Python :: 3
Classifier: Programming Language :: Python :: 3.6
Classifier: Intended Audience :: Developers
Classifier: Topic :: Software Development :: Libraries
Classifier: Topic :: Software Development :: Libraries :: Python Modules
Requires-Dist: requests
Requires-Dist: pytz
Requires-Dist: python-dateutil
